stickney-0.8.0.dist-info/METADATA
stickney-0.8.0.dist-info/WHEEL
stickney-0.8.0.dist-info/entry_points.txt
stickney-0.8.0.dist-info/licenses/LICENCE
stickney-0.8.0.dist-info/licenses/LICENCE.GPL
stickney/__init__.py
stickney/client.py
stickney/exc.py
stickney/frame.py
stickney/py.typed
stickney/sim.py
stickney-0.8.0.dist-info/RECORD
