Metadata-Version: 2.1
Name: stickney
Version: 0.8.0
Summary: Asynchronous websockets library
Author-Email: Lura Skye <fuyukaii@proton.me>
License: LGPL-3.0-or-later
Requires-Python: >=3.13
Requires-Dist: wsproto>=1.2.0
Requires-Dist: anyio>=4.1.0
Requires-Dist: attrs>=23.1.0
